wctools/__init__.py
wctools/image/__init__.py
wctools/image/img_format.py
wctools/image/size_manupilation.py
wctools/image_wc/__init__.py
wctools/image_wc/img_format.py
wctools/image_wc/size_manupilation.py
wctools/numpy/__init__.py
wctools/numpy/frequencies.py
wctools/numpy/np.py
wctools/numpy_wc/__init__.py
wctools/numpy_wc/frequencies.py
wctools/numpy_wc/np.py
wctools/plt/__init__.py
wctools/plt/barh.py
wctools/plt_wc/__init__.py
wctools/plt_wc/barh.py
wctools/yaml/__init__.py
wctools/yaml/yaml.py
wctools/yaml_wc/__init__.py
wctools/yaml_wc/yaml.py
wctools-0.2.20201224.dist-info/METADATA
wctools-0.2.20201224.dist-info/WHEEL
wctools-0.2.20201224.dist-info/top_level.txt
wctools-0.2.20201224.dist-info/RECORD
